gemini_sample_game/gemini_sample_game.py
gemini_sample_game-1.2.dist-info/LICENSE
gemini_sample_game-1.2.dist-info/METADATA
gemini_sample_game-1.2.dist-info/WHEEL
gemini_sample_game-1.2.dist-info/entry_points.txt
gemini_sample_game-1.2.dist-info/top_level.txt
gemini_sample_game-1.2.dist-info/RECORD
