Metadata-Version: 2.1
Name: gemini_sample_game
Version: 1.2
Summary: This package contains implementation of a sample game with Google Gemini AI integrated into it.
Home-page: https://github.com/GlobalCreativeApkDev/gemini_sample_game
Author: GlobalCreativeApkDev
Author-email: globalcreativeapkdev2022@gmail.com
License: MIT
Classifier: Programming Language :: Python :: 3
Classifier: Programming Language :: Python :: 3.7
License-File: LICENSE
